PythonPals/.gitkeep
PythonPals/Attendance.xlsx
PythonPals/Button.py
PythonPals/C1.png
PythonPals/C2.png
PythonPals/C3.png
PythonPals/C4.png
PythonPals/JandaManateeSolid.ttf
PythonPals/Ruby_Idle.png
PythonPals/Ruby_fire.png
PythonPals/Ruby_hurt.png
PythonPals/Ruby_left.png
PythonPals/Ruby_prep.png
PythonPals/Ruby_start.png
PythonPals/Snake_Firemid.png
PythonPals/Snake_fire_end.png
PythonPals/Snake_start.png
PythonPals/__init__.py
PythonPals/bluth.wav
PythonPals/cave.jpg
PythonPals/coffee1.png
PythonPals/coffee2.png
PythonPals/coffee3.png
PythonPals/coffee4.png
PythonPals/coffee5.png
PythonPals/coffee6.png
PythonPals/correct.wav
PythonPals/defaite.mp3
PythonPals/funke.mp3
PythonPals/goldmine.jpg
PythonPals/idle.wav
PythonPals/incorrect.wav
PythonPals/jazz.mp3
PythonPals/jungleBackground.jpg
PythonPals/lava.png
PythonPals/level_up.wav
PythonPals/main.py
PythonPals/ocean.jpg
PythonPals/player.py
PythonPals/python_questions.xlsx
PythonPals/python_questions_capitals.xlsx
PythonPals/python_questions_extra.xlsx
PythonPals/python_questions_timeline.xlsx
PythonPals/questions.py
PythonPals/requirements.txt
PythonPals/snake1.PNG
PythonPals/snake2.PNG
PythonPals/snake4.png
PythonPals/snake5.png
PythonPals/snake6.png
PythonPals/treasure.jpg
PythonPals/victoire.mp3
PythonPals-2.0.52.data/data/PythonPals/C1.png
PythonPals-2.0.52.data/data/PythonPals/C2.png
PythonPals-2.0.52.data/data/PythonPals/C3.png
PythonPals-2.0.52.data/data/PythonPals/C4.png
PythonPals-2.0.52.data/data/PythonPals/JandaManateeSolid.ttf
PythonPals-2.0.52.data/data/PythonPals/Ruby_Idle.png
PythonPals-2.0.52.data/data/PythonPals/Ruby_fire.png
PythonPals-2.0.52.data/data/PythonPals/Ruby_hurt.png
PythonPals-2.0.52.data/data/PythonPals/Ruby_left.png
PythonPals-2.0.52.data/data/PythonPals/Ruby_prep.png
PythonPals-2.0.52.data/data/PythonPals/Ruby_start.png
PythonPals-2.0.52.data/data/PythonPals/Snake_Firemid.png
PythonPals-2.0.52.data/data/PythonPals/Snake_fire_end.png
PythonPals-2.0.52.dist-info/METADATA
PythonPals-2.0.52.dist-info/WHEEL
PythonPals-2.0.52.dist-info/entry_points.txt
PythonPals-2.0.52.dist-info/top_level.txt
PythonPals-2.0.52.dist-info/RECORD
