Metadata-Version: 2.1
Name: PythonPals
Version: 2.0.52
Summary: Production Release
Home-page: https://github.com/nathanhilton/PythonPals/tree/development
Author: Sheamus Cooper
Author-email: sheamus.cooper@ufl.edu
License: UNKNOWN
Platform: UNKNOWN
Classifier: Programming Language :: Python :: 3
